[["Map",1,2,9,10],"meta::meta",["Map",3,4,5,6,7,8],"astro-config-digest","{\"root\":{},\"srcDir\":{},\"publicDir\":{},\"outDir\":{},\"cacheDir\":{},\"site\":\"https://vicwithgg-portfolio.vercel.app\",\"compressHTML\":true,\"base\":\"/\",\"trailingSlash\":\"ignore\",\"output\":\"static\",\"scopedStyleStrategy\":\"attribute\",\"build\":{\"format\":\"directory\",\"client\":{},\"server\":{},\"assets\":\"_assets\",\"serverEntry\":\"entry.mjs\",\"redirects\":false,\"inlineStylesheets\":\"auto\",\"concurrency\":4},\"server\":{\"open\":false,\"host\":false,\"port\":4321,\"streaming\":true,\"allowedHosts\":[]},\"redirects\":{},\"prefetch\":{\"prefetchAll\":false,\"defaultStrategy\":\"hover\"},\"image\":{\"endpoint\":{\"route\":\"/_image\"},\"service\":{\"entrypoint\":\"@astrojs/vercel/dev-image-service\",\"config\":{\"limitInputPixels\":100000000,\"formats\":[\"avif\",\"webp\"],\"sizes\":[640,750,828,1080,1200,1920,2048,3840],\"domains\":[\"placehold.co\"],\"remotePatterns\":[{\"protocol\":\"https\"}]}},\"domains\":[\"placehold.co\"],\"remotePatterns\":[{\"protocol\":\"https\"}],\"responsiveStyles\":false,\"breakpoints\":[640,750,828,1080,1200,1920,2048,3840]},\"devToolbar\":{\"enabled\":true},\"markdown\":{\"syntaxHighlight\":{\"type\":\"shiki\",\"excludeLangs\":[\"math\"]},\"shikiConfig\":{\"langs\":[],\"langAlias\":{},\"theme\":\"github-dark-dimmed\",\"themes\":{},\"wrap\":true,\"transformers\":[]},\"remarkPlugins\":[],\"rehypePlugins\":[],\"remarkRehype\":{},\"gfm\":true,\"smartypants\":{\"backticks\":true,\"closingQuotes\":{\"double\":\"”\",\"single\":\"’\"},\"dashes\":true,\"ellipses\":true,\"openingQuotes\":{\"double\":\"“\",\"single\":\"‘\"},\"quotes\":true}},\"security\":{\"checkOrigin\":true,\"allowedDomains\":[],\"csp\":false,\"actionBodySizeLimit\":1048576,\"serverIslandBodySizeLimit\":1048576},\"env\":{\"schema\":{},\"validateSecrets\":false},\"prerenderConflictBehavior\":\"warn\",\"experimental\":{\"clientPrerender\":false,\"contentIntellisense\":false,\"chromeDevtoolsWorkspace\":false,\"svgo\":false,\"rustCompiler\":false,\"queuedRendering\":{\"enabled\":false}},\"legacy\":{\"collectionsBackwardsCompat\":false}}","astro-version","6.1.2","content-config-digest","3d2257ba59fd7d97","proyectos",["Map",11,12,33,34,47,48,60,61,77,78,93,94,108,109,121,122,136,137,150,151,163,164,177,178,199,200,213,214,227,228,240,241,253,254,270,271,283,284,301,302],"adventours-mex",{"id":11,"data":13,"body":29,"filePath":30,"digest":31,"deferredRender":32},{"name":14,"sector":15,"description":16,"thumbnail":17,"tech":18,"links":22,"featured":25,"type":26,"order":27,"draft":25,"publishedDate":28},"AdvenTours Mex","E-commerce · Web","Creación de sitio web comercial, participando en la arquitectura web y diseño UI.","/images/projects/thumbnail-adven-tours.webp",[19,20,21],"Figma","UX/UI","Frontend",{"live":23,"figma":24},"https://adventoursmex.com/","https://www.figma.com/community/file/1570939876630705647/diseno-web-para-agencia-de-viajes",false,"web",4,"2026-01-15","## 🎯 Visión General\n\n[Breve párrafo describiendo el propósito del proyecto, tu rol y duración.]\n\n> **Rol:** [Tu rol específico]  \n> **Duración:** [Periodo]  \n> **Contexto:** [Cliente personal / freelance / académico]\n\n---\n\n## 💡 Solución Clave\n\n- **Punto diferencial 1:** [Descripción breve]\n- **Punto diferencial 2:** [Descripción breve]\n- **Punto diferencial 3:** [Descripción breve]\n\n---\n\n## ⚙️ Stack Técnico\n\n| Tecnología | Propósito        |\n| ---------- | ---------------- |\n| [Tech 1]   | [Uso específico] |\n| [Tech 2]   | [Uso específico] |\n| [Tech 3]   | [Uso específico] |\n\n---\n\n## 📊 Resultados\n\n- [Métrica o logro cuantificable 1]\n- [Métrica o logro cuantificable 2]\n- [Feedback destacado de cliente/usuario]\n\n---\n\n## 🔗 Enlaces\n\n- [🌐 Sitio en producción]({links.live})\n- [💻 Código en GitHub]({links.github})\n- [🎨 Diseño en Figma]({links.figma})","src/content/proyectos/adventours-Mex.mdx","ad66d119fff232bb",true,"app-healthcheck-smartwatch",{"id":33,"data":35,"body":29,"filePath":45,"digest":46,"deferredRender":32},{"name":36,"sector":37,"description":38,"thumbnail":39,"tech":40,"links":41,"featured":25,"type":43,"order":44,"draft":25},"App Healthcheck - Smartwatch y Mobile","UI/UX Design · Wearables","App de seguimiento de salud para móviles y wearables.","/images/projects/thumbnail-healtcheck.webp",[19,20],{"live":42,"figma":42},"https://www.figma.com/community/file/1270644133161232117","design",16,"src/content/proyectos/app-healthcheck-smartwatch.mdx","24bb2bcbe5538d57","arquitectura-ux-healthcheck",{"id":47,"data":49,"body":29,"filePath":58,"digest":59,"deferredRender":32},{"name":50,"sector":51,"description":52,"thumbnail":53,"tech":54,"links":55,"featured":25,"type":43,"order":57,"draft":25},"Arquitectura y UX de app HealthCheck","Arquitectura de Información · UX","Mapas de navegación y wireflows para HealthCheck.","/images/projects/thumbnail-arqH.webp",[19,20],{"live":56,"figma":56},"https://www.figma.com/community/file/1125658163306261422",17,"src/content/proyectos/arquitectura-ux-healthcheck.mdx","c92f971ac8334357","bit-tournament-2023",{"id":60,"data":62,"body":29,"filePath":75,"digest":76,"deferredRender":32},{"name":63,"sector":64,"description":65,"thumbnail":66,"tech":67,"links":70,"featured":25,"type":73,"order":74,"draft":25},"BIT Tournament 2023","Web App · Esports","Diseño UI y desarrollo frontend en Angular.","/images/projects/thumbnail-BIT.webp",[68,69,21],"Angular","TypeScript",{"live":71,"github":71,"figma":72},"https://github.com/Francisco-0510/BIT-TOURNAMENT-2023","https://www.figma.com/community/file/1165464149403530205/diseno-de-interfaces-bit-tournament-2023","app",18,"src/content/proyectos/bit-tournament-2023.mdx","4d87e54ab4765d5c","cv-minimalista",{"id":77,"data":79,"body":29,"filePath":91,"digest":92,"deferredRender":32},{"name":80,"sector":81,"description":82,"thumbnail":83,"tech":84,"links":87,"featured":25,"type":26,"order":90,"draft":25},"CV Minimalista (Web y PDF)","Web · Herramienta","CV minimalista en Web y PDF, configurable con JSON.","/images/projects/thumbnail-cv.webp",[19,85,20,86],"Design System","Responsive Design",{"live":88,"github":89},"https://vicwithgg.netlify.app/","https://github.com/Francisco-0510/minimalist-portfolio",8,"src/content/proyectos/cv-minimalista.mdx","82d20e7a9de62078","desarrollo-sistema-gestion-actividades",{"id":93,"data":95,"body":29,"filePath":106,"digest":107,"deferredRender":32},{"name":96,"sector":97,"description":98,"thumbnail":99,"tech":100,"links":103,"featured":25,"type":73,"order":105,"draft":25},"Desarrollo Front-end de Sistema Web de Gestión de Actividades","Web App · Educación","Desarrollo frontend con Ionic para sistema UTVCO.","/images/projects/thumbnail-tutoriasDev.webp",[101,102,69],"HTML5","Ionic",{"live":104,"github":104},"https://github.com/Francisco-0510/plataformaEstadias",14,"src/content/proyectos/desarrollo-sistema-gestion-actividades.mdx","5afb85a9df7a8ecc","diseno-sistema-gestion-actividades",{"id":108,"data":110,"body":29,"filePath":119,"digest":120,"deferredRender":32},{"name":111,"sector":112,"description":113,"thumbnail":114,"tech":115,"links":116,"featured":25,"type":43,"order":118,"draft":25},"Diseño de Sistema Web de Gestión de Actividades","UI/UX Design · Educación","Investigación y diseño UX/UI para sistema web.","/images/projects/thumbnail-tutoriasDesign.webp",[19,20,85],{"live":117,"figma":117},"https://www.figma.com/community/file/1205620325712950079",13,"src/content/proyectos/diseno-sistema-gestion-actividades.mdx","1cc807e18549c5cd","hospital-angel-del-mar",{"id":121,"data":123,"body":133,"filePath":134,"digest":135,"deferredRender":32},{"name":124,"sector":125,"description":126,"thumbnail":127,"tech":128,"links":130,"featured":25,"type":26,"order":132,"draft":25},"Hospital Ángel del Mar","Salud · Healthcare / Institutional Web","Rediseño del sitio web institucional del Hospital Ángel del Mar en Puerto Escondido. Sistema visual completo con directorio médico verificable, buscador de especialidades, y arquitectura de información diseñada para funcionar tanto en exploración planificada como en urgencia médica.","/images/projects/thumbnail-ham.webp",[19,85,129,20,86],"Webflow",{"live":131},"https://hospitalangeldelmar.com.mx/",10,"## 🎯 Visión General\n\nEl Hospital Ángel del Mar (HAM) es una institución médico-quirúrgica privada afiliada al Consorcio Mexicano de Hospitales, con múltiples clínicas especializadas, atención de emergencias 24/7, y un equipo de especialistas certificados en Puerto Escondido, Oaxaca. Sin embargo, su presencia digital no comunicaba ninguna de estas fortalezas.\n\n> **Headline del proyecto:** Rediseñé el sitio web de un hospital privado 24/7 para que cualquier persona pueda encontrar al especialista correcto — o el número de urgencias — en menos de 5 segundos.\n\n**Metadatos del proyecto:**\n\n| Campo        | Detalle               |\n| ------------ | --------------------- |\n| Proyecto     | HAM Website           |\n| Rol          | UX/UI Designer        |\n| Plataforma   | Desktop Web (1440px)  |\n| Herramientas | Figma · Design System |\n\n---\n\n## 01 · Problema\n\n### Un hospital de primer nivel sin una presencia digital que lo demostrara\n\nUn paciente que buscaba un especialista en Puerto Escondido no encontraba información confiable sobre el hospital: qué especialidades ofrece, qué médicos lo atienden, ni cómo contactarlo en una emergencia. La fricción digital le costaba pacientes reales al hospital.\n\n### Pain points detectados\n\n1. **Descubribilidad cero** — Sin un directorio de especialistas organizado, los pacientes no sabían quién los podía atender, qué clínicas existían, ni cuáles eran sus credenciales. La confianza médica requiere transparencia — y no había ninguna.\n2. **Urgencias sin señalización de acceso** — Un hospital 24/7 con servicios de emergencia no tenía un número de contacto prominente en su sitio. En un momento de crisis, el usuario no debería necesitar más de 2 segundos para encontrar cómo llamar.\n3. **Falta de jerarquía de servicios** — HAM opera clínicas especializadas (Mujer, Diabético, Enfermedades Digestivas, Pediátrica), hemodiálisis, laboratorio y farmacia. Sin arquitectura de información clara, esos servicios eran invisibles para el usuario.\n4. **Credibilidad institucional sin comunicar** — HAM está regulado por NOM Oficiales y afiliado al Consorcio Mexicano de Hospitales. Estos activos de confianza nunca llegaban al usuario porque no tenían espacio en el diseño anterior.\n\n### Datos del contexto\n\n| Métrica | Situación                                                           |\n| ------- | ------------------------------------------------------------------- |\n| 10+     | Clínicas y servicios especializados sin visibilidad digital         |\n| 24/7    | Atención de emergencias sin número prominente en web                |\n| 0 seg   | Lo que debería tardar el usuario en encontrar contacto de urgencias |\n\n---\n\n## 02 · Objetivos\n\n### Tres conversiones que el diseño debe lograr\n\nEl sitio web de HAM tiene tres CTA críticos: encontrar un especialista, contactar en urgencias, y conocer los servicios disponibles. Cada sección del diseño responde a uno de estos objetivos.\n\n**Business Goals:**\n\n- Aumentar consultas generadas vía web\n- Posicionar como hospital de referencia regional en Puerto Escondido\n- Diferenciarse de clínicas locales sin afiliación institucional\n- Reducir llamadas de información al mostrar datos clave en web\n- Amplificar la credibilidad del Consorcio Mexicano\n  **User Goals:**\n- Encontrar un especialista verificado en minutos\n- Confirmar que el hospital atiende mi padecimiento específico\n- Llegar al número de urgencias sin buscar\n- Conocer ubicación exacta y horarios sin llamar\n- Generar confianza antes de ir al hospital\n\n### KPIs potenciales (hipótesis de medición)\n\n| KPI                | Descripción                                          |\n| ------------------ | ---------------------------------------------------- |\n| Click-to-call rate | % de visitas que hacen tap en el número de urgencias |\n| Search engagement  | Uso del buscador de especialidades y condiciones     |\n| Doctor card CTR    | Clics en \"Ver especialista\" por tarjeta de médico    |\n| Maps interaction   | Clics al mapa embed en la sección de contacto        |\n\n---\n\n## 03 · Research\n\n### Usuarios, contexto y comportamiento en momentos críticos\n\nEn un sitio de salud, el contexto emocional del usuario varía drásticamente: desde una búsqueda planificada de especialista hasta una emergencia con alta carga de estrés. El diseño debe funcionar en ambos extremos sin sacrificar ninguno.\n\n> **Hipótesis de research:** Los usuarios de salud en contextos regionales como Puerto Escondido priorizan **credibilidad** (nombre del médico, cédula profesional) sobre estética. La confianza se construye con datos verificables, no con fotografías de stock.\n\n### User Personas\n\n**👩 Madre de familia** · 35–50 años · Puerto Escondido\nBusca pediatra o ginecólogo de confianza. Revisa credenciales antes de llamar. Decide en base a referencias sociales.\n\n> _\"Quiero saber que el médico que verá a mi hijo tiene sus papeles en regla antes de ir.\"_\n\n**👴 Paciente crónico** · 55–70 años · Paciente recurrente\nPadecimiento de diabetes o enfermedad renal. Necesita saber si el hospital maneja su condición y tiene los servicios de soporte (farmacia, lab, hemodiálisis).\n\n> _\"Necesito un lugar que tenga todo en un mismo lugar para no andar corriendo.\"_\n\n**🏥 Turista en emergencia** · 25–45 años · Visitante en Puerto Escondido\nTurista nacional o extranjero que necesita atención urgente. Llega al sitio con stress elevado. Necesita el número de teléfono y la dirección en segundos.\n\n> _\"Sólo necesito saber a dónde ir y a quién llamar. Ahora.\"_\n\n### Jobs To Be Done\n\n- **Cuando…** tengo una urgencia médica a las 2am → **Quiero…** encontrar el número de contacto del hospital en menos de 5 segundos, **para…** poder actuar sin perder tiempo buscando información.\n- **Cuando…** busco un especialista para una condición específica → **Quiero…** ver al médico, su especialidad y sus cédulas, **para…** saber que tiene la capacitación formal para atenderme.\n- **Cuando…** evalúo si este hospital es confiable → **Quiero…** ver credenciales institucionales, testimonios de pacientes y una imagen clara de las instalaciones, **para…** confiar antes de pagar por atención privada.\n\n---\n\n## 04 · Proceso UX\n\n### De la urgencia a la información, con cero fricción\n\nLa arquitectura del sitio resuelve dos modos de uso simultáneamente: el modo urgencia (alto estrés, necesita datos de contacto ahora) y el modo exploración (tiempo disponible, busca el médico correcto). El user flow principal prioriza el primero sin sacrificar el segundo.\n\n### User Flow principal\n\n```\n[Hero — Frase + contacto] → [Buscar Especialidad] → [Explorar Servicios (tabs)] → [Directorio Médicos] → [Confianza — Testimonios] → [Contacto — Mapa + datos]\n```\n\n### Decisiones de arquitectura clave\n\n**A — Contacto de urgencias en el hero, no en el footer**\nEl número de urgencias (954 103 4110) y el teléfono de recepción (954 177 0692) aparecen visibles en el hero como información contextual, no enterrados al fondo. Esta decisión responde directamente al JTBD del usuario en crisis.\n\n**B — Tabs en lugar de scroll infinito para servicios**\nCon 10+ clínicas y servicios, el scroll lineal crea fatiga. El sistema de tabs con pills agrupa los servicios por categoría (clínicas especializadas, diagnóstico, hospitalización), permitiendo al usuario ir directo a lo que necesita sin escanear toda la lista.\n\n**C — Buscador de especialidades centrado como acción principal**\nLa sección de búsqueda de especialidades usa un datalist + CTA centrado al 100% del ancho, jerarquizando esta acción como la más importante después del hero. La posición central y el espacio negativo guían la atención naturalmente.\n\n**D — Directorio de médicos con cédulas visibles en la tarjeta**\nCada Card Doctor muestra nombre, cédula profesional y cédula de especialidad. Esta decisión no es estética — es de confianza. Para el usuario, ver \"Ced. Prof: 3297941\" transforma al médico de anónimo a verificable. El costo visual es mínimo; el impacto en confianza es alto.\n\n### Navegación: jerarquía y acceso rápido\n\nLa barra de navegación principal (1440px, 80px de alto) incluye 6 items con dropdowns en \"Sobre Nosotros\" y \"Servicios\", un campo de búsqueda inline, y un switcher de idioma — demostrando que el hospital recibe pacientes turistas y entiende la necesidad bilingüe de Puerto Escondido como destino internacional.\n\nItems de navegación: `Inicio` · `Sobre Nosotros ↓` · `Urgencias` · `Promociones` · `Servicios ↓` · `Contáctanos` · `🔍 Buscar` · `🌐 Lang`\n\n---\n\n## 05 · UI Design\n\n### Un sistema visual que construye confianza médica\n\nEl sistema de diseño de HAM parte de una premisa clara: en salud, la confianza se construye con claridad, no con decoración. El color verde médico como primario no es accidental — activa asociaciones culturales de salud, higiene y profesionalismo.\n\n### Color Strategy\n\n| Paleta                 | Hex                   | Uso                                                   |\n| ---------------------- | --------------------- | ----------------------------------------------------- |\n| Verde médico (Primary) | `#1a7a4a`             | Brand color, CTAs, accents, iconografía               |\n| Verde oscuro           | `#062e1c` → `#0e5433` | Fondos hero, gradientes institucionales               |\n| Verde claro            | `#a8e6c5` / `#e8f5ee` | Highlights, fondos de sección                         |\n| Lila (Secondary)       | `#6B4ED6`             | Botones secundarios, Sobre Nosotros, acento editorial |\n| Neutral (UI)           | `#1a1917` → `#f8f7f4` | Tipografía, fondos, divisores, estados desactivados   |\n\n### Sistema de botones\n\nEl sistema de botones define 4 variantes con roles específicos, evitando la ambigüedad de acción:\n\n| Variante                        | Rol                                                |\n| ------------------------------- | -------------------------------------------------- |\n| **Primary** (verde relleno)     | Acción principal: agendar, buscar                  |\n| **Secondary** (verde outline)   | Acción de navegación: ver más, conocer             |\n| **Tertiary** (verde subrayado)  | Acción inline de bajo compromiso                   |\n| **Primary Lila** (lila relleno) | Acción institucional: Sobre Nosotros, afiliaciones |\n\n### Sistema de tags\n\nLos tags funcionan como etiquetas de clasificación para servicios, clínicas y especialidades. Su tamaño reducido (24px de altura) permite apilarlos en tarjetas sin competir con el título.\n\nEjemplos: `Clínica de la Mujer` · `Urgencias 24/7` · `Consulta Externa` · `Cirugía` · `Diagnóstico`\n\n### Componentes clave del sistema\n\n| Componente         | Descripción                                                                         |\n| ------------------ | ----------------------------------------------------------------------------------- |\n| 🃏 Card Servicio   | Icono SVG + Tag categoría + Título + Descripción + CTA terciario. Grid 3 columnas.  |\n| 👨‍⚕️ Card Doctor     | Foto + Nombre + Cédulas + Tags clínica/especialidad + CTA primario full-width.      |\n| 💬 Card Comentario | Quote text + Avatar (64px rounded) + Nombre + Rol. Grid 3 columnas.                 |\n| 🔍 Datalist Search | Input con autocomplete de especialidades + botón CTA. Centrado en sección dedicada. |\n| 📑 Tabs / Pill     | Navegación por categoría de servicios. Pills style, 1200px ancho. Activo en green.  |\n| 📸 Carousel 3-up   | Imagen central destacada (529px) flanqueada por previews laterales. Instalaciones.  |\n| 🗺️ Contact + Map   | Split layout: datos de contacto iconificados (izq.) + mapa embed full (der. 784px). |\n| 🎯 Featured Icon   | Icono con contenedor 48px + label + CTA inline. Usado en sección de contacto.       |\n\n### Iconografía: sistema duotono\n\nEl diseño utiliza un sistema de iconos duotono (Two-Colors) para los servicios del hero y bicolor para el navbar. Esta decisión eleva la percepción de calidad sin requerir ilustraciones complejas — el duotono en verde/verde-claro refuerza la identidad cromática en cada punto de contacto.\n\n> **Decisión de accesibilidad:** El cambio de idioma (ícono mdi:language en navbar) y la visibilidad del número de emergencias reflejan que el hospital atiende una audiencia mixta: residentes locales, turistas nacionales y extranjeros. El switcher de idioma es una decisión UX, no solo de UI.\n\n---\n\n## 06 · Pantallas Clave\n\n### Cada sección tiene un trabajo que hacer\n\n**Pantalla 01 — Hero: \"¡Tu SALUD y la de tu familia en BUENAS MANOS!\"**\n\n\u003Ciframe\n  style=\"border: 1px solid rgba(0, 0, 0, 0.1);\"\n  width=\"800\"\n  height=\"450\"\n  src=\"https://embed.figma.com/proto/4YoJl2Snui84vWfMs7rqUZ/HAM?node-id=1-26436&viewport=424%2C-765%2C0.15&scaling=scale-down-width&content-scaling=fixed&page-id=0%3A1&embed-host=share\"\n  allowfullscreen\n>\u003C/iframe>\n\n**Objetivo:** Capturar la atención, comunicar la promesa de marca, y dar acceso inmediato a información de emergencias.\n\n**Decisión UX:** El hero no tiene solo imagen + headline. Incluye un bloque de datos de contacto estructurado (icono + label + dato) que funciona como tarjeta de presentación rápida. El usuario puede salir del sitio en 3 segundos con toda la información que necesita en una urgencia.\n\n- Servicio 24 Hrs.\n- Urgencias: 954 103 4110\n- Dirección: Sexta Norte, PEO\n  **Decisión UI:** El headline usa texto con capitalización selectiva (\"SALUD\", \"BUENAS MANOS\") para crear jerarquía tipográfica sin cambiar de familia. Es un recurso de copywriting que el diseño respeta.\n\n---\n\n**Pantalla 02 — Buscador de Especialidades: Acción centrada**\n\n**Objetivo:** Resolver el JTBD de búsqueda específica — \"tengo una condición y quiero saber si este hospital la atiende\".\n\n**Decisión UX:** Sección dedicada centrada al 100%, con contexto de heading + subheading antes del input. El datalist (autocomplete) reduce la fricción de escritura y asegura que el usuario use los términos correctos del sistema. El botón \"Buscar\" es explícito y necesario — no hay submit por Enter como único mecanismo.\n\n---\n\n**Pantalla 03 — Servicios: Sistema de tabs con cards**\n\n**Objetivo:** Presentar 10+ clínicas y servicios sin abrumar. Permitir que el usuario filtre por categoría sin scroll infinito.\n\n**Decisión UX:** Los tabs tipo pill son la solución correcta para una colección de 10+ ítems heterogéneos. Agrupa los servicios en 4 categorías lógicas:\n\n- Clínicas especializadas\n- Diagnóstico\n- Hospitalización\n- Servicios de apoyo\n  El tab activo en verde refuerza la marca.\n\n---\n\n**Pantalla 04 — Directorio de Médicos: Confianza como componente**\n\n**Objetivo:** Presentar al equipo médico de forma que el usuario pueda verificar credenciales y elegir especialista con confianza.\n\n**Decisión de diseño:** La Card Doctor es el componente más crítico del sistema. Su estructura sigue una jerarquía de confianza: Foto (humaniza) → Nombre completo (identifica) → Cédula Profesional y Cédula de Especialidad (verifica) → Tags de clínica y especialidad (contextualiza) → CTA \"Agendar consulta\" (convierte).\n\n---\n\n**Pantalla 05 — Carousel de Instalaciones**\n\n**Objetivo:** Responder la pregunta no formulada: \"¿es este un hospital real y profesional?\"\n\n**Decisión UX:** El carousel de 3 imágenes (una central destacada de 529px flanqueada por previews) no es decorativo — es una herramienta de reducción de ansiedad pre-visita. Para un paciente nuevo, visualizar el entorno antes de ir reduce la barrera de decisión significativamente.\n\n---\n\n**Pantalla 06 — Testimonios**\n\n**Objetivo:** Reducir la fricción de decisión final. Después de ver los servicios y los médicos, los testimonios funcionan como validación social.\n\n**Decisión de posicionamiento:** Los testimonios aparecen antes de la sección de contacto, no después. La secuencia es: información (servicios + médicos) → confianza (testimonios) → acción (contacto). Invertirlo reduciría la tasa de conversión porque el usuario llegaría al CTA sin haber construido confianza.\n\n---\n\n## 07 · Retos\n\n### Los trade-offs que definen el diseño\n\n**🔄 Actualización de contenido médico**\nEl directorio de médicos contiene cédulas, clínicas y fotos de cada especialista. Un hospital cambia su plantilla con frecuencia.\n✓ Componentes atómicos en Figma permiten actualizar tarjetas sin romper el sistema. El componente Card Doctor es una instancia reutilizable.\n\n**📱 Desktop-first con alto riesgo mobile**\nEl diseño está pensado para 1440px. Los usuarios en emergencias probablemente lleguen desde móvil. La jerarquía de urgencias debe sobrevivir en pantalla pequeña.\n✓ La información de emergencias (número, 24hrs, dirección) está estructurada con componentes flex que colapsan bien en columna.\n\n**🗂️ Densidad de información vs. claridad**\n10+ clínicas, 6+ médicos por especialidad, múltiples datos de contacto. El riesgo es un sitio denso y confuso.\n✓ Tabs para servicios, filtro por especialidad para médicos, y secciones dedicadas con máximo 3 elementos visibles por defecto.\n\n**🌐 Audiencia bilingüe**\nPuerto Escondido es destino turístico con visitantes internacionales que pueden necesitar atención médica. El switcher de idioma en navbar debe estar donde el ojo lo busca.\n✓ Language switcher posicionado en el extremo derecho del navbar, consistente con convenciones web internacionales.\n\n**📊 Sin métricas base previas**\nSin analytics históricos del sitio anterior es imposible establecer un baseline de conversión. Los KPIs se definen como hipótesis de medición, no como comparativas.\n✓ Se priorizan métricas de comportamiento (click-to-call, search engagement) sobre métricas de resultado que requieren tiempo para acumular.\n\n**🏥 Regulación institucional**\nComo hospital regulado por NOM y afiliado al Consorcio Mexicano, ciertos datos (cédulas, afiliaciones) deben mostrarse con precisión exacta, limitando libertad de copywriting.\n✓ Los datos regulatorios se presentan como datos de confianza, no como obligación legal. El \"Afiliado al Consorcio Mexicano de Hospitales\" es un valor que convence, no un disclaimer.\n\n---\n\n## 📊 Resultados\n\n> **Nota metodológica:** Los resultados son proyecciones razonadas basadas en benchmarks del sector salud digital y los cambios específicos implementados en el diseño. No son datos reales medidos post-lanzamiento — se marcan como hipótesis.\n\n| Métrica | Impacto esperado                                                             | Justificación                                 |\n| ------- | ---------------------------------------------------------------------------- | --------------------------------------------- |\n| ↑ 3×    | Aumento en click-to-call desde el hero vs. footer-only                       | Hipótesis · Benchmark healthcare UX           |\n| -60%    | Reducción en llamadas de información básica (horarios, dirección, servicios) | Hipótesis · Basado en contenido ahora visible |\n| +40%    | Mejora en tiempo de descubrimiento de especialista correcto                  | Hipótesis · Tabs + filtro vs. scroll lineal   |\n\n### Impacto cualitativo\n\n- **Credibilidad institucional visible** — La afiliación al Consorcio Mexicano de Hospitales y el cumplimiento de NOM ahora tienen espacio en el diseño. Para el usuario no iniciado, esto transforma a HAM de \"una clínica más\" a \"un hospital con respaldo institucional\".\n- **El hospital como referencia regional** — Un directorio médico completo con cédulas verificables convierte al sitio de HAM en la fuente de referencia para especialidades en Puerto Escondido — potencialmente recibiendo tráfico orgánico que el hospital nunca capturó antes.\n- **Reducción de fricción en la decisión de pagar** — En salud privada, el mayor bloqueador de conversión es la duda: \"¿es este hospital lo suficientemente bueno para que yo pague?\" El flujo testimonios → contacto responde esa duda justo antes del momento de acción.\n\n---\n\n## 09 · Aprendizajes\n\n### Lo que este proyecto enseña sobre diseño en salud\n\n1. **La información de emergencia es una decisión de diseño, no de contenido** — Dónde colocas el número de urgencias determina si alguien puede usarlo en un momento de pánico. Esto no se resuelve con buena redacción — se resuelve con jerarquía visual y posicionamiento intencional. El héroe es el único lugar correcto.\n2. **En salud, la confianza se construye con datos verificables, no con aspiración** — Una fotografía bonita del lobby no convence a nadie de confiar su salud a un hospital. Un número de cédula profesional con nombre completo, sí. El diseño debe facilitar la verificación, no esconderla detrás de estética.\n3. **La componentización hace escalable un sistema de información médica** — Médicos cambian, clínicas abren, servicios se añaden. Un sistema de componentes atómicos (Card Doctor, Card Servicio, Tag) permite al hospital actualizar su contenido sin rediseñar. El valor del diseño no está en las pantallas, está en el sistema.\n4. **Mejoras futuras priorizadas** — Las siguientes iteraciones deberían incluir: (1) diseño mobile-first paralelo al desktop, (2) sistema de citas online integrado, (3) sección de promociones con filtro por tipo de seguro/aseguradora, y (4) micro-animaciones en el tab de servicios para guiar la atención al contenido activo.\n\n---\n\n## 10 · Insights UX\n\n### Principios que guiaron cada decisión\n\n- **El estrés del usuario define la jerarquía.** En salud, la arquitectura de información debe diseñarse para el estado emocional más crítico del usuario: la emergencia. Todo lo que importa en urgencia debe ser accesible en 0–3 segundos.\n- **Los tabs no son navegación — son filtros de contenido.** El sistema de tabs para servicios no navega a otra página; filtra el contenido visible. Esta distinción UX elimina la ruptura de contexto y mantiene al usuario en su journey de exploración.\n- **La prueba social debe ir antes del CTA, no después.** Los testimonios inmediatamente antes de la sección de contacto operan como último persuasor antes de la decisión. Moverlos al footer — como es común — los hace invisibles para la mayoría de los usuarios.\n- **Un CTA full-width en cards médicas elimina la ambigüedad de acción.** Cuando hay múltiples elementos informativos en una tarjeta, el ojo no sabe qué elemento es clickeable. Un botón que ocupa el 100% del ancho de la tarjeta resuelve esta ambigüedad sin diseño adicional.\n- **El idioma en el navbar no es una feature — es accesibilidad.** Puerto Escondido recibe miles de turistas internacionales anualmente. Un switcher de idioma en el navbar convierte el hospital en accesible para pacientes que no hablan español, en el momento en que más lo necesitan.\n- **El carousel de instalaciones responde al question \"¿es esto profesional?\".** La galería de fotos del hospital no está por estética — está para que el usuario pueda visualizar el entorno antes de ir. Es una herramienta de reducción de ansiedad pre-visita, especialmente para pacientes nuevos.","src/content/proyectos/hospital-angel-del-mar.mdx","c9dcbe309be09e42","portafolio-braquetes",{"id":136,"data":138,"body":29,"filePath":148,"digest":149,"deferredRender":32},{"name":139,"sector":140,"description":141,"thumbnail":142,"tech":143,"links":145,"featured":25,"type":26,"order":147,"draft":25},"Portafolio braquetes.com.mx","Portafolio · Web","Portafolio web para programador backend.","/images/projects/coverBR.webp",[101,144],"Bootstrap",{"live":146},"https://www.braquetes.com.mx/#/",12,"src/content/proyectos/portafolio-braquetes.mdx","a366f5a9b42b48e7","rediseño-app-healthcheck",{"id":150,"data":152,"body":29,"filePath":161,"digest":162,"deferredRender":32},{"name":153,"sector":154,"description":155,"thumbnail":156,"tech":157,"links":158,"featured":25,"type":43,"order":160,"draft":25},"Rediseño App HealthCheck","UI/UX Design · Salud","Rediseño de app HealthCheck para dispositivos móviles.","/images/projects/thumbnail-rediseño.webp",[19,20,85],{"figma":159},"https://www.figma.com/community/file/1283078639346112182",15,"src/content/proyectos/rediseño-app-healthcheck.mdx","e451fc758fc58e4d","seguridad-privada-betaj",{"id":163,"data":165,"body":29,"filePath":175,"digest":176,"deferredRender":32},{"name":166,"sector":167,"description":168,"thumbnail":169,"tech":170,"links":172,"featured":25,"type":26,"order":174,"draft":25},"Seguridad Privada BETAJ","Corporativo · Web","Diseño de interfaces y desarrollo en Webflow.","/images/projects/thumbnail-betaj.webp",[101,171,129],"React",{"live":173},"https://betaj.mx/",11,"src/content/proyectos/seguridad-privada-betaj.mdx","9a54bd928e4210fa","sicroa",{"id":177,"data":179,"body":196,"filePath":197,"digest":198,"deferredRender":32},{"name":180,"sector":181,"description":182,"thumbnail":183,"tech":184,"links":194,"featured":32,"type":73,"order":195,"draft":25},"SiCROA","Gobierno · Aeronáutica","SiCROA - Sistema de Control y Registro de Operaciones Aéreas. Plataforma digital para centralizar, controlar y optimizar procesos operativos del entorno aeronáutico con arquitectura modular, design system integrado y escalabilidad enterprise. Módulos de personal, capacitaciones y documentos.","/images/projects/thumbnail-sicroa.webp",[185,69,186,187,188,189,190,191,192,193,19],"React 19","Vite","Tailwind CSS","Node.js","Express","PostgreSQL","TypeORM","TanStack Query","Radix UI",{},1,"## 🎯 Visión General\n\n**SiCROA - HANGAR** (_Sistema Integral de Control de Operaciones Aeronáuticas_) es una plataforma enterprise diseñada para unidades de aviación gubernamentales y privadas que requieren centralizar y digitalizar sus procesos operativos críticos.\n\nLa arquitectura modular del sistema permite escalar funcionalidades según las necesidades de la organización, manteniendo coherencia visual mediante un Design System documentado y facilitando el trabajo colaborativo entre equipos técnicos, operativos y administrativos.\n\n**Impacto principal:**\n\n- ✅ Centralización de procesos operativos, de mantenimiento y administrativos en una única plataforma\n- ✅ Coherencia visual y funcional garantizada por un Design System integrado con Figma\n- ✅ Escalabilidad modular para adaptarse a diferentes tamaños de flota y complejidad operativa\n- ✅ Colaboración eficiente entre equipos técnicos y operativos con flujos de trabajo documentados\n\n## 📚 Introducción y Guías Generales\n\n### 1.1. Propósito del Documento\n\nEste manual tiene como objetivo guiar a los usuarios en el uso eficiente y seguro del sistema, proporcionando una referencia visual y funcional de cada módulo, pantalla y componente. Sirve como fuente única de verdad para:\n\n- Onboarding de nuevos usuarios y equipos\n- Consulta rápida de funcionalidades y flujos de trabajo\n- Estándares de implementación para desarrolladores\n- Criterios de aceptación para QA y testing\n\n### 1.2. SiCROA - HANGAR\n\nSiCROA es una plataforma digital diseñada para centralizar, controlar y optimizar los procesos operativos del entorno aeronáutico. Su arquitectura modular permite:\n\n- 🧩 **Escalabilidad funcional**: Añadir nuevos módulos sin afectar el núcleo del sistema\n- 🎨 **Coherencia visual**: Design System unificado que garantiza consistencia en toda la interfaz\n- 🤝 **Trabajo colaborativo**: Herramientas y flujos que conectan equipos técnicos y operativos\n- 🔐 **Gobernanza integrada**: Roles, permisos y auditoría nativos en cada capa de la aplicación\n\n### 1.3. Audiencia del Manual\n\n| Perfil                          | Responsabilidades                                  | Secciones clave                                         |\n| ------------------------------- | -------------------------------------------------- | ------------------------------------------------------- |\n| **Usuarios operativos**         | Despacho, seguimiento y control aéreo              | Módulos de vuelo, alertas, reportes                     |\n| **Administradores del sistema** | Configuración, gestión de usuarios y permisos      | Panel de administración, RBAC, auditoría                |\n| **Equipos técnicos**            | Desarrollo, implementación y extensión del sistema | Arquitectura, API, Design System, guías de contribución |\n\n### 1.4. Uso del Design System en el Manual\n\nEl manual se apoya directamente en el Design System completo y el diseño de interfaces documentados en Figma, lo que asegura coherencia entre diseño y desarrollo.\n\n#### 🔹 Fundamentos Visuales\n\n- **Tipografía**: Escala tipográfica basada en `Montserrat` `Inter` con jerarquías definidas para títulos, cuerpos y etiquetas\n\n\u003Ciframe\n  style=\"border: 1px solid rgba(0, 0, 0, 0.1);\"\n  width=\"800\"\n  height=\"450\"\n  src=\"https://embed.figma.com/proto/lTBaJen234WiWJmRP648lH/Dise%C3%B1o-UX-UI-Hangar?node-id=161398-61592&p=f&viewport=622%2C1702%2C0.38&scaling=scale-down&content-scaling=fixed&page-id=101%3A8500&embed-host=share\"\n  allowfullscreen\n>\u003C/iframe>\n\n- **Paleta de colores**: Sistema semántico con tokens para primarios, estados (success/warning/error) y modos claro/oscuro.}\n\n\u003Ciframe\n  style=\"border: 1px solid rgba(0, 0, 0, 0.1);\"\n  width=\"800\"\n  height=\"450\"\n  src=\"https://embed.figma.com/proto/lTBaJen234WiWJmRP648lH/Dise%C3%B1o-UX-UI-Hangar?node-id=103-8753&p=f&viewport=131%2C964%2C0.17&scaling=contain&content-scaling=fixed&page-id=103%3A246&embed-host=share\"\n  allowfullscreen\n>\u003C/iframe>\n\n- **Espaciados**: Escala de 4px para márgenes, paddings y gaps consistente en toda la aplicación\n\n\u003Ciframe\n  style=\"border: 1px solid rgba(0, 0, 0, 0.1);\"\n  width=\"800\"\n  height=\"450\"\n  src=\"https://embed.figma.com/proto/lTBaJen234WiWJmRP648lH/Dise%C3%B1o-UX-UI-Hangar?node-id=105-299&p=f&viewport=263%2C93%2C0.09&scaling=contain&content-scaling=fixed&page-id=179%3A29802&embed-host=share\"\n  allowfullscreen\n>\u003C/iframe>\n\n- **Jerarquía visual**: Patrones de composición para cards, secciones y páginas que guían la atención del usuario\n\n#### Componentes Base\n\n| Componente       | Estados                                   | Accesibilidad                       |\n| ---------------- | ----------------------------------------- | ----------------------------------- |\n| Button           | default, hover, active, disabled, loading | ARIA labels, focus visible          |\n| Input / Textarea | default, focus, error, success            | Labels asociados, mensajes de ayuda |\n| Badge / Tag      | info, success, warning, error             | Contraste WCAG AA, texto legible    |\n| Modal / Drawer   | open, closing, backdrop                   | Focus trap, escape key, ARIA modal  |\n\n#### 🔹 Componentes de Aplicación\n\n- **Tablas avanzadas**: Sorting, filtering, pagination y acciones en lote con TanStack Table\n- **Navegación**: Sidebar colapsable, breadcrumbs y menú contextual adaptativo\n- **Cards informativas**: Patrones para KPIs, resúmenes de entidad y vistas preliminares\n- **Formularios complejos**: Wizards, validación en tiempo real y guardado automático\n\n\u003Ciframe\n  style=\"border: 1px solid rgba(0, 0, 0, 0.1);\"\n  width=\"800\"\n  height=\"450\"\n  src=\"https://embed.figma.com/proto/lTBaJen234WiWJmRP648lH/Dise%C3%B1o-UX-UI-Hangar?page-id=299%3A3695&node-id=161398-63711&p=f&viewport=68%2C315%2C0.02&scaling=contain&content-scaling=fixed&embed-host=share\"\n  allowfullscreen\n>\u003C/iframe>\n\n#### 🔹 Buenas Prácticas Integradas\n\n- ♿ **Accesibilidad**: Cumplimiento WCAG 2.1 AA, roles ARIA semánticos y navegación por teclado\n- 🎯 **Consistencia**: Patrones de interacción reutilizables y lenguaje uniforme en toda la plataforma\n- 🚀 **Escalabilidad**: Componentes diseñados con props extensibles y hooks reutilizables\n- 🌐 **Internacionalización**: Estructura preparada para i18n con separación de contenido y lógica\n\n## 💡 Solución Clave\n\n- **Arquitectura monorepo escalable**: Separación clara entre frontend (React + Vite) y backend (Node.js + Express) comunicándose exclusivamente vía API REST versionada `/api/v1`, facilitando el mantenimiento y despliegue independiente.\n\n- **Módulos funcionales especializados**: 8 dominios de negocio interconectados que cubren el ciclo completo de operaciones aéreas.\n\n- **Design System integrado con Figma**: Componentes documentados, tokens de diseño sincronizados y prototipos interactivos que reducen la brecha entre diseño y desarrollo.\n\n- **Integración con servicios externos**: Conexión segura con APIs de NOTAM (NMS-API) y datos meteorológicos (AWC), permitiendo planificación de vuelos con información actualizada sin salir de la plataforma.\n\n- **Gestión documental inteligente**: Sistema de alertas automáticas para vencimiento de documentos de personal y aeronaves, con almacenamiento seguro de archivos y generación de PDFs para reportes oficiales.\n\n## ⚙️ Stack Técnico\n\n| Tecnología                  | Uso                                                 | Versión      |\n| --------------------------- | --------------------------------------------------- | ------------ |\n| **React**                   | Framework principal de UI                           | 19.x         |\n| **TypeScript**              | Lenguaje tipado para frontend y backend             | 5.9          |\n| **Vite**                    | Build tool y dev server para frontend               | 7.x          |\n| **Tailwind CSS**            | Estilizado utilitario y diseño responsive           | 4.x          |\n| **Radix UI**                | Primitivos de UI accesibles (vía shadcn/ui)         | latest       |\n| **TanStack Query**          | Gestión de estado del servidor y caché              | 5.x          |\n| **TanStack Table**          | Tablas avanzadas con sorting, filtering, pagination | 8.x          |\n| **React Router**            | Enrutamiento del lado del cliente                   | 7.x          |\n| **Node.js**                 | Runtime del servidor backend                        | ≥20          |\n| **Express**                 | Framework para API REST                             | 5.x          |\n| **TypeORM**                 | ORM para gestión de base de datos                   | 0.3.x        |\n| **PostgreSQL**              | Base de datos relacional principal                  | —            |\n| **jsonwebtoken + bcryptjs** | Autenticación JWT y hashing de contraseñas          | 9.x / 3.x    |\n| **Multer + Sharp**          | Procesamiento y optimización de archivos            | 2.x / 0.34.x |\n| **node-cron**               | Ejecución de tareas programadas (alertas, backups)  | 4.x          |\n| **Swagger**                 | Documentación interactiva de la API                 | —            |\n| **Figma**                   | Diseño de interfaces y Design System                | —            |\n| **pnpm**                    | Gestor de paquetes eficiente para monorepo          | 10           |\n\n## 📊 Resultados\n\n- **📈 Eficiencia operativa**: Reducción del 40% en tiempo de planificación de vuelos mediante automatización de cálculos de peso y balance con generación automática de formularios PDF.\n\n- **🔒 Cumplimiento y seguridad**: 100% de trazabilidad en operaciones críticas con sistema de auditoría de cambios, RBAC granular y headers de seguridad configurados.\n\n- **⚡ Rendimiento técnico**: Carga inicial \u003C 2s gracias a code-splitting con Vite, caching inteligente con TanStack Query y optimización de imágenes con Sharp.\n\n- **🎨 Consistencia de diseño**: 95% de reutilización de componentes del Design System, reduciendo tiempo de desarrollo de nuevas vistas en un 60%.\n\n- **📊 Visibilidad en tiempo real**: Dashboards con KPIs actualizados al instante, exportación de reportes a Excel/PDF y alertas proactivas para vencimientos de documentación.\n\n- **🔄 Escalabilidad probada**: Arquitectura preparada para crecimiento, con monorepo estructurado, API versionada y separación de responsabilidades que permite añadir nuevos módulos sin impacto en funcionalidades existentes.","src/content/proyectos/sicroa.mdx","849a25eabbbde057","sistema-boletos-solteca",{"id":199,"data":201,"body":29,"filePath":211,"digest":212,"deferredRender":32},{"name":202,"sector":203,"description":204,"thumbnail":205,"tech":206,"links":207,"featured":25,"type":73,"order":210,"draft":25},"Sistema Venta de Boletos La Solteca","Web App · Transporte","Diseño y desarrollo de sistema de venta de boletos.","/images/projects/thumbnail-soltecaDesign.webp",[68,69,20],{"live":208,"github":209},"https://xd.adobe.com/view/5b7241f4-f464-4276-69b2-89a327b55523-2d43/","https://github.com/Francisco-0510/Solteca",20,"src/content/proyectos/sistema-boletos-solteca.mdx","3ea35b1d3fbf10be","spotify-clone",{"id":213,"data":215,"body":29,"filePath":225,"digest":226,"deferredRender":32},{"name":216,"sector":217,"description":218,"thumbnail":219,"tech":220,"links":222,"featured":25,"type":73,"order":224,"draft":25},"Spotify Clone","Web App · Clone","Réplica funcional de la interfaz de Spotify con tecnologías modernas.","https://placehold.co/600x400/0b0f18/3a7bd5?text=Spotify+Clone&font=roboto",[221,171,187,21],"Astro",{"github":223},"https://github.com/Francisco-0510/spotify-clone",5,"src/content/proyectos/spotify-clone.mdx","1e8edb0efca0cab0","taaniilaaz-muneco-chocolate",{"id":227,"data":229,"body":237,"filePath":238,"digest":239,"deferredRender":32},{"name":230,"sector":231,"description":232,"thumbnail":233,"tech":234,"links":235,"featured":25,"type":43,"order":236,"draft":25},"Taaniilaaz y Muñeco de Chocolate","UI/UX Design · Branding","Rediseño completo de interfaz de usuario (UI/UX) y diseño de identidad visual.","https://placehold.co/600x400/0b0f18/3a7bd5?text=Taaniilaaz&font=roboto",[19,20,86],{},3,"## 🎯 Visión General\n\n[Breve párrafo describiendo el propósito del proyecto, tu rol y duración.]\n\n> **Rol:** [Tu rol específico]  \n> **Duración:** [Periodo]  \n> **Contexto:** [Cliente personal / freelance / académico]\n\n---\n\n## 💡 Solución Clave\n\n- **Punto diferencial 1:** [Descripción breve]\n- **Punto diferencial 2:** [Descripción breve]\n- **Punto diferencial 3:** [Descripción breve]\n\n---\n\n## ⚙️ Stack Técnico\n\n| Tecnología | Propósito        |\n| ---------- | ---------------- |\n| [Tech 1]   | [Uso específico] |\n| [Tech 2]   | [Uso específico] |\n| [Tech 3]   | [Uso específico] |\n\n---\n\n## 📊 Resultados\n\n- [Métrica o logro cuantificable 1]\n- [Métrica o logro cuantificable 2]\n- [Feedback destacado de cliente/usuario]\n\n---\n\n## 🔗 Enlaces","src/content/proyectos/taaniilaaz-muneco-chocolate.mdx","87e71d2274a28052","user-story-mapping-bit-tournament",{"id":240,"data":242,"body":29,"filePath":251,"digest":252,"deferredRender":32},{"name":243,"sector":244,"description":245,"thumbnail":246,"tech":247,"links":248,"featured":25,"type":43,"order":250,"draft":25},"User Story Mapping - BIT TOURNAMENT 2023","UX Research · Agile","Historias de usuario y mapas de navegación para BIT Tournament.","/images/projects/thumbnail-storyBIT.webp",[19,20],{"live":249,"figma":249},"https://www.figma.com/community/file/1183832840468301220/user-story-mapping-bit-tournament-2023",19,"src/content/proyectos/user-story-mapping-bit-tournament.mdx","eea13d5edfbba60c","utvco-gestion-cultural-deportiva",{"id":253,"data":255,"body":267,"filePath":268,"digest":269,"deferredRender":32},{"name":256,"sector":257,"description":258,"thumbnail":259,"tech":260,"links":262,"featured":32,"type":26,"order":265,"draft":25,"publishedDate":266,"updatedDate":266},"Sistema Web Para La Gestión de Actividades Culturales y Deportivas","Educación · Gestión Académica","Plataforma web para optimizar el registro y seguimiento de actividades culturales y deportivas. Diseñada con enfoque UX/UI centrado en el usuario.","/images/projects/thumbnail-sistema-utvco.webp",[85,21,69,187,19,261],"Ionic Framework",{"live":263,"github":264},"https://www.figma.com/deck/lUapPq3OwsMbiz6TfQqdSP/Presentaci%C3%B3n-Titulacion?node-id=34-244&t=1LByIleGRKAlSQay-1&scaling=min-zoom&content-scaling=fixed&page-id=0%3A1","https://github.com/Francisco-0510/activity-management-system",2,"2025-09-10","## **Case Study: Sistema Web para la Gestión de Actividades Culturales y Deportivas de la UTVCO – Frontend**\n\n**Autor:** Aguirre Jiménez Francisco Victorico  \n**Rol:** Diseñador UX/UI & Desarrollador Frontend  \n**Institución:** Universidad Tecnológica de los Valles Centrales de Oaxaca (UTVCO)  \n**Fecha de presentación:** Proyecto de titulación (2026)\n\n### 1. Contexto y Cliente\n\nLa Universidad Tecnológica de los Valles Centrales de Oaxaca (UTVCO) imparte diversas actividades culturales y deportivas a través del área de Cultura y Deportes. Estas actividades son un pilar fundamental para la formación integral de los estudiantes. Sin embargo, la gestión de inscripciones y seguimiento se realizaba de forma manual mediante **Google Forms** y hojas de cálculo (Excel/Sheets), lo que generaba ineficiencias operativas graves.\n\n### 2. Planteamiento del Problema\n\nEl proceso actual presentaba tres problemas principales:\n\n- **Ineficiencia operativa**: Organización y clasificación de datos lenta y manual, con alto consumo de tiempo.\n- **Falta de control**: No existía un mecanismo automatizado para cerrar cupos o límites de inscripción.\n- **Dificultad administrativa**: Mala visualización de datos de inscritos, lo que complicaba la generación oportuna de reportes y el seguimiento de estudiantes.\n\nEstos problemas afectaban directamente a tres perfiles de usuarios:\n\n- **Estudiantes** (inscripción y consulta de actividades).\n- **Administradores** (gestión, reportes y control).\n- **Encargados de tutoría** (seguimiento académico).\n\n### 3. Objetivos del Proyecto\n\n**Objetivo General**  \nDiseñar las interfaces de usuario y desarrollar el **frontend** de un sistema web para la optimización y gestión automatizada de las inscripciones a las actividades culturales y deportivas de la UTVCO.\n\n**Objetivos Específicos**\n\n1. Analizar el proceso de inscripción y clasificación de datos del área de cultura y deportes.\n2. Diseñar la propuesta de solución aplicando **Design Thinking** y **Diseño Centrado en el Usuario (DCU/UCD)**.\n3. Desarrollar un prototipo funcional que demuestre funcionalidades e interacción.\n4. Codificar los componentes diseñados.\n5. Determinar los requerimientos funcionales y no funcionales.\n6. Diseñar las interfaces gráficas de todos los módulos del sistema.\n\n### 4. Metodologías Aplicadas\n\nSe combinaron tres enfoques complementarios:\n\n- **Design Thinking**: Para comprender profundamente al usuario y generar soluciones creativas.\n- **SCRUM**: Para un desarrollo iterativo y flexible.\n- **Diseño Centrado en el Usuario (DCU)**: Para garantizar usabilidad, accesibilidad y satisfacción real de las necesidades.\n\n### 5. Proceso de Design Thinking (Fases Detalladas)\n\n**Fase 1 – Empatizar**  \nSe realizaron investigaciones de usuarios, entrevistas (Customer Journey Interviews) con el Administrador (Lic. Julio César López Aguilar) y mapas de empatía. Se identificaron dolores de estudiantes (proceso confuso, falta de información) y administradores (gestión manual tediosa).\n\n**Fase 2 – Definir**  \nSe crearon **User Personas** (Estudiante, Administrador, Encargado de Tutoría) y se delimitó el problema central: “La gestión manual de inscripciones genera ineficiencia, falta de control y mala experiencia para todos los usuarios”.\n\n**Fase 3 – Idear**  \nSe diseñó la **Arquitectura de Información**, diagramas de flujo (estudiante y administrador) y mapas de navegación. Se generaron múltiples conceptos de solución priorizando simplicidad y automatización.\n\n**Fase 4 – Prototipar**  \nSe desarrollaron tres niveles:\n\n- Wireframes de baja fidelidad (papel).\n- Mockups de media fidelidad.\n- **Prototipo de alta fidelidad** (interactivo) en Figma, tanto para móvil (estudiante) como escritorio (administrador).\n\n**Fase 5 – Testear**  \nSe probaron los prototipos con usuarios reales para obtener feedback y realizar iteraciones antes de la implementación final.\n\n### 6. Tecnologías y Herramientas\n\n- **Figma**: Diseño colaborativo, prototipado y UI Kit completo (guía de estilos, tipografía Poppins, paleta institucional UTVCO, sombras, componentes).\n- **Ionic Framework**: Desarrollo del frontend para aplicaciones móviles de alto rendimiento y calidad (enfocado en UX/UI).\n- **Guía de Estilos (UI Kit)**: Tipografía, paleta de colores institucionales, escalas de grises, sombras y componentes estandarizados para mantener consistencia.\n\n### 7. Solución Implementada (Prototipo Funcional)\n\nSe entregó un **prototipo funcional de alta fidelidad** completamente navegable que incluye:\n\n**Para Usuario Estudiante (móvil):**\n\n- Splash screen con branding “Cultura & Deportes”.\n- Inicio de sesión / recuperación de contraseña.\n- Dashboard de actividades (Deportivas, Culturales y Grupales).\n- Tarjetas de actividades con botón “Descubrir”.\n- Formulario de inscripción paso a paso (3 pasos).\n- Pantalla de “Registro Exitoso”.\n\n**Para Usuario Administrador (escritorio):**\n\n- Dashboard con métricas rápidas (tutorías deportivas, culturales y grupales).\n- Menú lateral: Documentos, Usuarios (SuperAdmin, Administradores, Tutores), Actividades (Deportivas, Culturales, Grupales).\n- Lista de tutorías con filtros, búsqueda y estado (Deportiva/Cultural/Grupal).\n- Gestión de usuarios y reportes.\n\nEl sistema utiliza la **matrícula UTVCO** como identificador principal de login, garantizando seguridad y vinculación institucional.\n\n### 8. Resultados y Valor Entregado\n\nEl proyecto logró:\n\n- **Optimización del proceso**: Transformación completa de un sistema manual a uno automatizado y sistemático.\n- **Diseño centrado en el usuario**: Interfaz intuitiva, usable y accesible para los tres perfiles de usuario, maximizando adopción.\n- **Sistema listo para producción**: Prototipo de alta fidelidad + Guía de Estilos (UI Kit) robusta, permitiendo una transición fluida al equipo de backend.\n- **Funcionalidades clave validadas**:\n  - Control administrativo (reportes, filtros, cierre automático de cupos).\n  - Acceso seguro mediante matrícula institucional.\n  - Arquitectura escalable con roadmap futuro (comentarios, encuestas, funciones sociales).\n\n### 9. Conclusiones y Lecciones Aprendidas\n\nEste proyecto demuestra que un enfoque riguroso de **Design Thinking + DCU** permite resolver problemas reales de eficiencia operativa en instituciones educativas. Se entregó no solo una interfaz bonita, sino una solución funcional, usable y preparada para escalar.\n\n**Roadmap futuro**: Integración de funcionalidades sociales, notificaciones push y analíticas avanzadas.\n\nEl frontend desarrollado representa un paso significativo hacia la digitalización del área de Cultura y Deportes de la UTVCO, mejorando la experiencia de cientos de estudiantes y facilitando la labor administrativa.\n\n**¡Proyecto finalizado con éxito!**  \nListo para implementación completa del sistema web.\n\n### Recursos\n\n\u003Ciframe\n  style=\"border: 1px solid rgba(0, 0, 0, 0.1);\"\n  width=\"800\"\n  height=\"450\"\n  src=\"https://embed.figma.com/slides/lUapPq3OwsMbiz6TfQqdSP/Presentaci%C3%B3n-Titulacion?node-id=5-820&embed-host=share\"\n  allowfullscreen\n>\u003C/iframe>","src/content/proyectos/utvco-gestion-cultural-deportiva.mdx","c2569dd3ff8d69ef","vg-design-ui-kit",{"id":270,"data":272,"body":29,"filePath":281,"digest":282,"deferredRender":32},{"name":273,"sector":274,"description":275,"thumbnail":276,"tech":277,"links":278,"featured":25,"type":43,"order":280,"draft":25},"VG Design UI Kit","Design Systems · UI Kit","Kit de diseño UI/UX en Figma.","/images/projects/thumbnail-vg-design-ui-kit.webp",[19,85,86,20],{"figma":279},"https://www.figma.com/community/file/1273539501651863397/vg-design-ui-kit-v1-2-0",9,"src/content/proyectos/vg-design-ui-kit.mdx","a0c2f9a35faf6130","vgg-movies-search",{"id":283,"data":285,"body":29,"filePath":299,"digest":300,"deferredRender":32},{"name":286,"sector":287,"description":288,"thumbnail":289,"tech":290,"links":295,"featured":25,"type":73,"order":298,"draft":25},"VGG Movies Search","Web App · Entretenimiento","App para explorar y guardar películas favoritas, usando Firebase.","/images/projects/vgg-movie.webp",[171,291,292,293,294],"Chakra UI","Firebase","Vercel","GitHub",{"live":296,"github":297},"https://vgg-movie-search.vercel.app/","https://github.com/Francisco-0510/movie-app-react",7,"src/content/proyectos/vgg-movies-search.mdx","dbde49334efbc65e","vicwithgg-portfolio",{"id":301,"data":303,"body":29,"filePath":312,"digest":313,"deferredRender":32},{"name":304,"sector":140,"description":305,"thumbnail":306,"tech":307,"links":308,"featured":25,"type":26,"order":311,"draft":25},"VicWithGG Portafolio Web","Portafolio personal con Astro, Tailwind CSS y Netlify.","/images/projects/vicwithgg-cover.webp",[101,171,221,187,293,294],{"live":309,"github":310},"https://vicwithgg-designer.netlify.app/","https://github.com/Francisco-0510/vicwithgg-portfolio",6,"src/content/proyectos/vicwithgg-portfolio.mdx","e75c2b667d2c3d8e"]